{
  "action": "SKIP",
  "validation": {
    "valid": true,
    "requiresRepair": false,
    "reasons": []
  },
  "valid": true,
  "requiresRepair": false,
  "reasons": [],
  "dbData": {
    "header": {
      "id": 488,
      "company_code": "C0018",
      "tally_owner": "USER",
      "guid": "755da616-c913-46c0-9ad0-de5499d071a0-00000016",
      "masterid": "22",
      "alterid": 72,
      "voucher_type": "Sales",
      "voucher_number": "3",
      "voucher_date": "2026-07-01",
      "effective_date": "2026-07-01",
      "reference": null,
      "reference_date": null,
      "party_ledger": "Mammohan",
      "narration": null,
      "gstin": "06BASDPSDPSDPSP",
      "place_of_supply": "Haryana",
      "buyer_name": "Mammohan",
      "buyer_address": null,
      "gst_registration_type": "Regular",
      "persisted_view": "Invoice Voucher View",
      "is_invoice": true,
      "is_optional": false,
      "is_cancelled": false,
      "last_synced_at": "2026-07-23T18:36:07.981",
      "sync_batch_id": "TEST001",
      "is_deleted": false,
      "created_at": "2026-07-23T18:11:42.053795",
      "updated_at": "2026-07-23T18:36:07.981"
    },
    "ledgers": [
      {
        "id": 1829,
        "voucher_guid": "755da616-c913-46c0-9ad0-de5499d071a0-00000016",
        "company_code": "C0018",
        "tally_owner": "USER",
        "ledger_name": "Mammohan",
        "ledger_masterid": "239",
        "amount": -2040,
        "debit": 2040,
        "credit": 0,
        "is_deemed_positive": "true",
        "is_party_ledger": "true",
        "is_last_deemed_positive": "true",
        "remove_zero_entries": "false",
        "bill_allocations": [
          {
            "amount": -2040,
            "dueDate": "",
            "billName": 3,
            "billType": "New Ref",
            "creditDays": 0
          }
        ],
        "costcentre_allocations": [],
        "created_at": "2026-07-23T18:36:12.406306",
        "ledger_guid": "755da616-c913-46c0-9ad0-de5499d071a0-000000ef",
        "ledger_alterid": "283",
        "ledger_parent_name": "Sundry Debtors",
        "ledger_parent_guid": "755da616-c913-46c0-9ad0-de5499d071a0-00000014",
        "ledger_parent_masterid": "20",
        "ledger_parent_alterid": "21"
      },
      {
        "id": 1830,
        "voucher_guid": "755da616-c913-46c0-9ad0-de5499d071a0-00000016",
        "company_code": "C0018",
        "tally_owner": "USER",
        "ledger_name": "Local Sale 20%",
        "ledger_masterid": "240",
        "amount": 1700,
        "debit": 0,
        "credit": 250,
        "is_deemed_positive": "false",
        "is_party_ledger": "false",
        "is_last_deemed_positive": "false",
        "remove_zero_entries": "false",
        "bill_allocations": [],
        "costcentre_allocations": [],
        "created_at": "2026-07-23T18:36:12.406306",
        "ledger_guid": "755da616-c913-46c0-9ad0-de5499d071a0-000000f0",
        "ledger_alterid": "286",
        "ledger_parent_name": "Sales Accounts",
        "ledger_parent_guid": null,
        "ledger_parent_masterid": "23",
        "ledger_parent_alterid": "24"
      },
      {
        "id": 1831,
        "voucher_guid": "755da616-c913-46c0-9ad0-de5499d071a0-00000016",
        "company_code": "C0018",
        "tally_owner": "USER",
        "ledger_name": "CGST 10%",
        "ledger_masterid": "2370",
        "amount": 170,
        "debit": 250,
        "credit": 170,
        "is_deemed_positive": "false",
        "is_party_ledger": "false",
        "is_last_deemed_positive": "false",
        "remove_zero_entries": "false",
        "bill_allocations": [],
        "costcentre_allocations": [],
        "created_at": "2026-07-23T18:36:12.406306",
        "ledger_guid": "755da616-c913-46c0-9ad0-de5499d071a0-000000ed",
        "ledger_alterid": "277",
        "ledger_parent_name": "Duties & Taxes",
        "ledger_parent_guid": null,
        "ledger_parent_masterid": "14",
        "ledger_parent_alterid": "15"
      },
      {
        "id": 1832,
        "voucher_guid": "755da616-c913-46c0-9ad0-de5499d071a0-00000016",
        "company_code": "C0018",
        "tally_owner": "USER",
        "ledger_name": "SGST 10%",
        "ledger_masterid": "241241",
        "amount": 170,
        "debit": 0,
        "credit": 170,
        "is_deemed_positive": "false",
        "is_party_ledger": "false",
        "is_last_deemed_positive": "false",
        "remove_zero_entries": "false",
        "bill_allocations": [],
        "costcentre_allocations": [],
        "created_at": "2026-07-23T18:36:12.406306",
        "ledger_guid": "755da616-c913-46c0-9ad0-de5499d071a0-000000f1",
        "ledger_alterid": "285",
        "ledger_parent_name": "Duties & Taxes",
        "ledger_parent_guid": "755da616-c913-46c0-9ad0-de5499d071a0-0000000e",
        "ledger_parent_masterid": "14",
        "ledger_parent_alterid": "15"
      }
    ],
    "inventory": [
      {
        "id": 297,
        "voucher_guid": "755da616-c913-46c0-9ad0-de5499d071a0-00000016",
        "company_code": "C0018",
        "tally_owner": "USER",
        "stock_item": "3/4 CPVC Elbow Heavy",
        "stock_masterid": "209",
        "actual_qty": "100 Nos",
        "actual_qty_value": 100,
        "billed_qty": "100 Nos",
        "billed_qty_value": 100,
        "unit": "Nos",
        "rate": "17.00/Nos",
        "rate_value": 17,
        "amount": 1700,
        "hsn_code": "3918",
        "discount": 0,
        "godown": "Main Location",
        "batches": [
          {
            "rate": "17.00/Nos",
            "amount": 1700,
            "godown": "Main Location",
            "actualQty": "100 Nos",
            "batchName": "Primary Batch",
            "billedQty": "100 Nos"
          }
        ],
        "accounting": [
          {
            "amount": 1700,
            "ledgerName": "Local Sale 20%",
            "ledgerMasterId": ""
          }
        ],
        "gst_rates": [
          {
            "rate": 10,
            "perUnit": 0,
            "dutyHead": "CGST",
            "valuationType": "Based on Value"
          },
          {
            "rate": 10,
            "perUnit": 0,
            "dutyHead": "SGST/UTGST",
            "valuationType": "Based on Value"
          },
          {
            "rate": 20,
            "perUnit": 0,
            "dutyHead": "IGST",
            "valuationType": "Based on Value"
          },
          {
            "rate": 0,
            "perUnit": 0,
            "dutyHead": "Cess",
            "valuationType": " Not Applicable"
          },
          {
            "rate": 0,
            "perUnit": 0,
            "dutyHead": "State Cess",
            "valuationType": "Based on Value"
          }
        ],
        "costcentre_allocations": [],
        "created_at": "2026-07-23T18:36:12.554901",
        "stock_guid": "755da616-c913-46c0-9ad0-de5499d071a0-000000d1",
        "stock_alterid": 292,
        "ledger_parent_guid": "755da616-c913-46c0-9ad0-de5499d071a0-00000017",
        "ledger_parent_master_id": "23",
        "ledger_parent_alter_id": 24,
        "cgst_rate": 10,
        "sgst_rate": 10,
        "igst_rate": 20,
        "gst_rate": 20,
        "cgst_amount": 170,
        "sgst_amount": 170,
        "igst_amount": 0,
        "taxable_amount": 1700,
        "voucher_date": "2026-07-01",
        "voucher_type": "Sales",
        "transaction_type": "Yes",
        "party_name": "Mammohan",
        "party_guid": "755da616-c913-46c0-9ad0-de5499d071a0-000000ef",
        "party_master_id": "239",
        "party_alter_id": 283,
        "ledger_name": "Local Sale 20%",
        "ledger_guid": "755da616-c913-46c0-9ad0-de5499d071a0-000000f0",
        "ledger_master_id": "240",
        "ledger_alter_id": 286,
        "ledger_parent_name": "Sales Accounts",
        "tax_type": null,
        "voucher_master_id": "22",
        "voucher_alter_id": 72,
        "party_parent_name": "Sundry Debtors",
        "party_parent_guid": "755da616-c913-46c0-9ad0-de5499d071a0-00000014",
        "party_parent_master_id": "20",
        "party_parent_alter_id": 21
      }
    ]
  }
}